traffy/__init__.py
traffy/client.py
traffy/exceptions.py
traffy/models.py
traffyapi-0.1.0.dist-info/METADATA
traffyapi-0.1.0.dist-info/WHEEL
traffyapi-0.1.0.dist-info/top_level.txt
traffyapi-0.1.0.dist-info/RECORD
