Metadata-Version: 2.4
Name: traffyapi
Version: 0.1.0
Summary: Async wrapper for Traffy API
Author-email: Azizbek <jumaevazizbeluz@gmail.com>
Requires-Python: >=3.8
Requires-Dist: aiohttp
